hufflescuff/__init__.py
hufflescuff/version.py
hufflescuff/widget.py
hufflescuff/data/planet_data.csv
hufflescuff-0.1.dist-info/METADATA
hufflescuff-0.1.dist-info/RECORD
hufflescuff-0.1.dist-info/WHEEL
hufflescuff-0.1.dist-info/top_level.txt
